{
    "akimgames": {
        "image": "https://static-cdn.jtvnw.net/previews-ttv/live_user_akimgames-320x180.jpg",
        "status": "Road To Platino!! |Twitter: @AkimAguilar |",
        "viewers": "207",
        "time": 1515650524.6519136
    },
    "gabeegaming": {
        "image": "https://static-cdn.jtvnw.net/previews-ttv/live_user_gabeegaming-320x180.jpg",
        "status": "[ES/EN] Holooo! ",
        "viewers": "20",
        "time": 1515650524.652412
    },
    "tytannia92": {
        "image": "https://static-cdn.jtvnw.net/previews-ttv/live_user_tytannia92-320x180.jpg",
        "status": "Despu\u00e9s de ver OWL me inspir\u00e9, de regreso a diamante!",
        "viewers": "19",
        "time": 1515650524.6529064
    },
    "playreactor": {
        "image": "https://static-cdn.jtvnw.net/previews-ttv/live_user_playreactor-320x180.jpg",
        "status": "[\ud83d\udd34 ] Veamos a Dallas Fuel vs. Seoul Dynasty. Luego a jugar!  \u00af\\_(\u30c4)_/\u00af ",
        "viewers": "18",
        "time": 1515650524.6533837
    },
    "atomika13": {
        "image": "https://static-cdn.jtvnw.net/previews-ttv/live_user_atomika13-320x180.jpg",
        "status": "Positivismo al 100 | Go to Diamnte  |  @atomika13_",
        "viewers": "15",
        "time": 1515650524.653909
    },
    "xchapy": {
        "image": "https://static-cdn.jtvnw.net/previews-ttv/live_user_xchapy-320x180.jpg",
        "status": "[ESP] Sus overwachos nocturnos\u300cS\u00f3lo MIC\u300d !! \u2605 Hagamos crecer m\u00e1s la familia \u2605 Gracias por participar.-",
        "viewers": "11",
        "time": 1515650524.6544094
    },
    "melohhh": {
        "image": "https://static-cdn.jtvnw.net/previews-ttv/live_user_melohhh-320x180.jpg",
        "status": "ow ! xD",
        "viewers": "11",
        "time": 1515650524.6544094
    },
    "denls97": {
        "image": "https://static-cdn.jtvnw.net/previews-ttv/live_user_denls97-320x180.jpg",
        "status": "Hola amigos :)\n",
        "viewers": "11",
        "time": 1515650524.6549115
    },
    "6metal6warrior6": {
        "image": "https://static-cdn.jtvnw.net/previews-ttv/live_user_6metal6warrior6-320x180.jpg",
        "status": "Overwatch - Competitive and Quick Match",
        "viewers": "10",
        "time": 1515650524.6554155
    },
    "yvettemarietta": {
        "image": "https://static-cdn.jtvnw.net/previews-ttv/live_user_yvettemarietta-320x180.jpg",
        "status": "ESP | ENG Overwatch para finalizar",
        "viewers": "10",
        "time": 1515650524.6559145
    },
    "huesitoduro": {
        "image": "https://static-cdn.jtvnw.net/previews-ttv/live_user_huesitoduro-320x180.jpg",
        "status": "HuesitoRanked 3300 SR Aprox.",
        "viewers": "10",
        "time": 1515650524.6559145
    },
    "aletz": {
        "image": "https://static-cdn.jtvnw.net/previews-ttv/live_user_aletz-320x180.jpg",
        "status": "El Primer Stream 2018! De Road to Platino",
        "viewers": "9",
        "time": 1515650524.6564105
    },
    "yuyitaaa": {
        "image": "https://static-cdn.jtvnw.net/previews-ttv/live_user_yuyitaaa-320x180.jpg",
        "status": " Meta 2018 llegar a oro en Overwatch :'v (1600 puntos)",
        "viewers": "8",
        "time": 1515650524.6569188
    },
    "tahi": {
        "image": "https://static-cdn.jtvnw.net/previews-ttv/live_user_tahi-320x180.jpg",
        "status": "Colocacion en pc -_- Probando nueva !senpc",
        "viewers": "7",
        "time": 1515650524.6574152
    },
    "alexnoobi": {
        "image": "https://static-cdn.jtvnw.net/previews-ttv/live_user_alexnoobi-320x180.jpg",
        "status": "\n[MEX] Necesito un squad perros",
        "viewers": "7",
        "time": 1515650524.6574152
    },
    "valkiriaunity": {
        "image": "https://static-cdn.jtvnw.net/previews-ttv/live_user_valkiriaunity-320x180.jpg",
        "status": "Manqueando en Overwatch pasenle a ver",
        "viewers": "6",
        "time": 1515650524.6578963
    },
    "kyngelric": {
        "image": "https://static-cdn.jtvnw.net/previews-ttv/live_user_kyngelric-320x180.jpg",
        "status": "[PS4/MX]  Main Reinhardt esta temporada :D! | Sigueme @Kyng_Elric",
        "viewers": "6",
        "time": 1515650524.6583972
    },
    "vampirocast": {
        "image": "https://static-cdn.jtvnw.net/previews-ttv/live_user_vampirocast-320x180.jpg",
        "status": "[ESP/ENG](XBOX)De regreso al oberguach \ud83d\ude02\ud83d\ude02\ud83d\ude02",
        "viewers": "6",
        "time": 1515650524.6588993
    },
    "lesly26_": {
        "image": "https://static-cdn.jtvnw.net/previews-ttv/live_user_lesly26_-320x180.jpg",
        "status": "Overwatch wooo",
        "viewers": "5",
        "time": 1515650524.6594005
    },
    "elfrankmeza": {
        "image": "https://static-cdn.jtvnw.net/previews-ttv/live_user_elfrankmeza-320x180.jpg",
        "status": "MIERCOLES DE RETOS...!! ",
        "viewers": "5",
        "time": 1515650524.6604152
    },
    "xanreed": {
        "image": "https://static-cdn.jtvnw.net/previews-ttv/live_user_xanreed-320x180.jpg",
        "status": "[ESP/PER\u00da] Competitivo en platinazo, camino a diamante :D",
        "viewers": "5",
        "time": 1515650524.6609151
    },
    "legendofjuli": {
        "image": "https://static-cdn.jtvnw.net/previews-ttv/live_user_legendofjuli-320x180.jpg",
        "status": "[ESP/COL] No me ver\u00e1 ni Dios pero igual har\u00e9 strum :') | D\u00eda 10/365",
        "viewers": "5",
        "time": 1515650524.6614048
    },
    "pukkov": {
        "image": "https://static-cdn.jtvnw.net/previews-ttv/live_user_pukkov-320x180.jpg",
        "status": "[MX] Vamos a competitivo",
        "viewers": "4",
        "time": 1515650524.6634114
    },
    "twistedmaggie": {
        "image": "https://static-cdn.jtvnw.net/previews-ttv/live_user_twistedmaggie-320x180.jpg",
        "status": "Movimiento naranja",
        "viewers": "4",
        "time": 1515650524.663914
    },
    "lexxray__": {
        "image": "https://static-cdn.jtvnw.net/previews-ttv/live_user_lexxray__-320x180.jpg",
        "status": "Overwatch competitivo (camino a diamante)",
        "viewers": "4",
        "time": 1515650524.664915
    },
    "blackrnemesis": {
        "image": "https://static-cdn.jtvnw.net/previews-ttv/live_user_blackrnemesis-320x180.jpg",
        "status": "Temporada 8 de Overwatch ",
        "viewers": "3",
        "time": 1515650524.6654158
    },
    "kreazzy": {
        "image": "https://static-cdn.jtvnw.net/previews-ttv/live_user_kreazzy-320x180.jpg",
        "status": "Como lo zupo !",
        "viewers": "3",
        "time": 1515650524.6654158
    },
    "duendeconker001": {
        "image": "https://static-cdn.jtvnw.net/previews-ttv/live_user_duendeconker001-320x180.jpg",
        "status": "aver como me va",
        "viewers": "3",
        "time": 1515650524.665948
    },
    "golhlive": {
        "image": "https://static-cdn.jtvnw.net/previews-ttv/live_user_golhlive-320x180.jpg",
        "status": "ft. Francisco bocallena y negra :v",
        "viewers": "3",
        "time": 1515650524.6664414
    },
    "nyuugamesyt": {
        "image": "https://static-cdn.jtvnw.net/previews-ttv/live_user_nyuugamesyt-320x180.jpg",
        "status": "\ud83d\udd34 Fortnite nocturno, Sims 4, Overwatch | Meta 200 followers \\_(*-*)_/ | #NyuSenpaiStreaming ",
        "viewers": "3",
        "time": 1515650524.6664414
    }
}